{
    "Name": "2014-12-24-Victoria",
    "ThumbPath": "",
    "Slides": [
        {
            "ImagePath": "20141225_0708-_GWR0153.jpg",
            "Description": "Christmas Tree"
        },
        {
            "ImagePath": "20141225_0710-_GWR0155.jpg",
            "Description": "Christmas Morning"
        },
        {
            "ImagePath": "20141225_1440-_GWR0160.jpg",
            "Description": "Bench"
        },
        {
            "ImagePath": "20141225_1447-_GWR0169.jpg",
            "Description": "People"
        },
        {
            "ImagePath": "20141225_1451-_GWR0175.jpg",
            "Description": "Island"
        },
        {
            "ImagePath": "20141225_1515-_GWR0178.jpg",
            "Description": "Dolls"
        },
        {
            "ImagePath": "20141225_1613-_GWR0185.jpg",
            "Description": "Makeup"
        },
        {
            "ImagePath": "20141225_1616-_GWR0187.jpg",
            "Description": "Makeup"
        },
        {
            "ImagePath": "20141226_1312-_GWR0190.jpg",
            "Description": "Depressing House"
        },
        {
            "ImagePath": "20141226_1313-_GWR0192.jpg",
            "Description": "Depressing House"
        },
        {
            "ImagePath": "20141226_1320-_GWR0193.jpg",
            "Description": "Ocean"
        },
        {
            "ImagePath": "20141226_1321-_GWR0201.jpg",
            "Description": "Outdoorsy cool looking Lianne"
        },
        {
            "ImagePath": "20141228_1105-_GWR0214.jpg",
            "Description": "Bike"
        },
        {
            "ImagePath": "20150101_1327-_GWR0229.jpg",
            "Description": "Amber and the Dog"
        },
        {
            "ImagePath": "20150101_1329-_GWR0235.jpg",
            "Description": "Sittin"
        },
        {
            "ImagePath": "20150103_1411-R0000255.jpg",
            "Description": "Vancouver"
        },
        {
            "ImagePath": "20150104_1345-R0000259.jpg",
            "Description": "Fence Art"
        }
    ]
}