{
    "Name": "2009-07-12-Rainforest Music Festival",
    "ThumbPath": "",
    "Slides": [
        {
            "ImagePath": "_DSC0203.jpg",
            "Description": "Inti Illimani"
        },
        {
            "ImagePath": "_DSC0240.jpg",
            "Description": "Zawose Family"
        },
        {
            "ImagePath": "_DSC0272.jpg",
            "Description": "Zawose Family"
        },
        {
            "ImagePath": "_DSC0399.jpg",
            "Description": "Besucher | Crowd"
        },
        {
            "ImagePath": "_DSC0541.jpg",
            "Description": "Inga und Abdul | Inga and Abdul"
        },
        {
            "ImagePath": "_DSC0581.jpg",
            "Description": "UK"
        },
        {
            "ImagePath": "_DSC0647.jpg",
            "Description": "Festivalteilnehmer | Visitors"
        },
        {
            "ImagePath": "_DSC0699.jpg",
            "Description": "Festivalteilnehmer | Visitors"
        },
        {
            "ImagePath": "_DSC0757.jpg",
            "Description": "Festivalteilnehmer | Visitors"
        }
    ]
}